{"metadata":{"tags":[{"sys":{"type":"Link","linkType":"Tag","id":"templatedContent"}}]},"sys":{"space":{"sys":{"type":"Link","linkType":"Space","id":"e4vn8tcbbhts"}},"type":"Entry","id":"476325671","contentType":{"sys":{"type":"Link","linkType":"ContentType","id":"media"}},"revision":1,"createdAt":"2023-06-30T15:34:28.625Z","updatedAt":"2023-07-11T15:30:34.185Z","environment":{"sys":{"id":"master","type":"Link","linkType":"Environment"}}},"fields":{"internalTitle":{"en-US":"Image - Person Walking"},"asset":{"en-US":{"sys":{"type":"Link","linkType":"Asset","id":"5ON6CUW9eT0MlfpxLhFzHJ"}}}}}